LICENSE
MANIFEST.in
README.md
README.rst
requirements.txt
setup.cfg
setup.py
rss_transmission.egg-info/PKG-INFO
rss_transmission.egg-info/SOURCES.txt
rss_transmission.egg-info/dependency_links.txt
rss_transmission.egg-info/requires.txt
rss_transmission.egg-info/top_level.txt
rssbot/__init__.py
rssbot/config.py
rssbot/default_settings.json
rssbot/feeds.py
rssbot/logger.py
rssbot/main.py
rssbot/models.py
rssbot/web.py
rssbot/static/css/app.d6c17de93bdc942fb8af9030709fbed8.css
rssbot/static/css/app.d6c17de93bdc942fb8af9030709fbed8.css.map
rssbot/static/js/app.da8b9bc6b8567fad689b.js
rssbot/static/js/app.da8b9bc6b8567fad689b.js.map
rssbot/static/js/manifest.c480bfd993d7b7d38f1c.js
rssbot/static/js/manifest.c480bfd993d7b7d38f1c.js.map
rssbot/static/js/vendor.b2eb89e18d88c6a43cb2.js
rssbot/static/js/vendor.b2eb89e18d88c6a43cb2.js.map
rssbot/templates/index.html