Metadata-Version: 1.1
Name: rss-transmission
Version: 0.1.0
Summary: Rss plugin for transmission with a web ui
Home-page: https://github.com/helloqiu/rss-transmission
Author: helloqiu
Author-email: helloqiu95@gmail.com
License: GPLv3
Keywords: rss transmission webui
Platform: UNKNOWN
Classifier: Development Status :: 1 - Planning
Classifier: License :: OSI Approved :: GNU General Public License v3 (GPLv3)
Classifier: Operating System :: MacOS
Classifier: Operating System :: POSIX
Classifier: Operating System :: POSIX :: Linux
Classifier: Programming Language :: Python
